pgtg/__init__.py
pgtg/constants.py
pgtg/environment.py
pgtg/evaluator.py
pgtg/example_maps/tile_map_big_with_obstacles.json
pgtg/example_maps/tile_map_big_without_obstacles.json
pgtg/example_maps/tile_map_medium_with_obstacles.json
pgtg/example_maps/tile_map_medium_without_obstacles.json
pgtg/example_maps/tile_map_minimal_without_obstacles.json
pgtg/graphic.py
pgtg/map.py
pgtg/map_generator.py
pgtg/map_tiles_data.py
pgtg/parser.py
pgtg/pics/beginning.png
pgtg/pics/road_break.png
pgtg/pics/road_left.png
pgtg/pics/test.png
pgtg-0.5.0.dist-info/METADATA
pgtg-0.5.0.dist-info/WHEEL
pgtg-0.5.0.dist-info/RECORD
