Metadata-Version: 2.3
Name: pgtg
Version: 0.5.0
Summary: Python simulation of a driving challange. Compatible with the Gymnasium API standard.
Author: Timo P. Gros
Author-email: timopgros@cs.uni-saarland.de
Requires-Python: >=3.10,<4.0
Classifier: Development Status :: 4 - Beta
Classifier: Intended Audience :: Science/Research
Classifier: Operating System :: OS Independent
Classifier: Programming Language :: Python :: 3
Classifier: Programming Language :: Python :: 3.10
Classifier: Programming Language :: Python :: 3.11
Classifier: Programming Language :: Python :: 3.12
Classifier: Programming Language :: Python :: 3.13
Classifier: Topic :: Scientific/Engineering :: Artificial Intelligence
Requires-Dist: Pillow (>=10.1,<11.0)
Requires-Dist: graph-theory (>=2022.4.3,<2023.0.0)
Requires-Dist: gymnasium (>=0.28.1,<0.29.0)
Requires-Dist: jupyter (>=1.0.0,<2.0.0)
Requires-Dist: matplotlib (>=3.4.3,<4.0.0)
Requires-Dist: numpy (>=1.26.3,<2.0.0)
Requires-Dist: pygame (>=2.5.2,<3.0.0)
